iMICSdset_utils/__init__.py
iMICSdset_utils/_mask.cpython-37m-x86_64-linux-gnu.so
iMICSdset_utils/coco.py
iMICSdset_utils/cocoeval.py
iMICSdset_utils/mask.py
iMICSdset_utils-1.0.0.dist-info/LICENSE
iMICSdset_utils-1.0.0.dist-info/METADATA
iMICSdset_utils-1.0.0.dist-info/WHEEL
iMICSdset_utils-1.0.0.dist-info/top_level.txt
iMICSdset_utils-1.0.0.dist-info/RECORD
